{
    "packageType": "Microcontrollers",
    "components": [
      {
        "text": [
          {
            "_x": "1.27",
            "_y": "54.61",
            "_size": "1.27",
            "_layer": "25",
            "__text": ">NAME"
          },
          {
            "_x": "1.27",
            "_y": "-2.54",
            "_size": "1.27",
            "_layer": "27",
            "__text": ">VALUE"
          }
        ],
        "wire": [
          {
            "_x1": "0.994481",
            "_y1": "53.2986",
            "_x2": "64.472",
            "_y2": "53.2986",
            "_width": "0.127",
            "_layer": "51"
          },
          {
            "_x1": "0.740569",
            "_y1": "53.2563",
            "_x2": "0.994481",
            "_y2": "53.2986",
            "_width": "0.127",
            "_layer": "51"
          },
          {
            "_x1": "0.507819",
            "_y1": "53.1505",
            "_x2": "0.740569",
            "_y2": "53.2563",
            "_width": "0.127",
            "_layer": "51"
          },
          {
            "_x1": "0.296231",
            "_y1": "53.0024",
            "_x2": "0.507819",
            "_y2": "53.1505",
            "_width": "0.127",
            "_layer": "51"
          },
          {
            "_x1": "0.126959",
            "_y1": "52.7908",
            "_x2": "0.296231",
            "_y2": "53.0024",
            "_width": "0.127",
            "_layer": "51"
          },
          {
            "_x1": "0.0423188",
            "_y1": "52.558",
            "_x2": "0.126959",
            "_y2": "52.7908",
            "_width": "0.127",
            "_layer": "51"
          },
          {
            "_x1": "0",
            "_y1": "52.283",
            "_x2": "0.0423188",
            "_y2": "52.558",
            "_width": "0.127",
            "_layer": "51"
          },
          {
            "_x1": "0",
            "_y1": "0.9931",
            "_x2": "0",
            "_y2": "52.283",
            "_width": "0.127",
            "_layer": "51"
          },
          {
            "_x1": "0.0423188",
            "_y1": "0.739191",
            "_x2": "0",
            "_y2": "0.9931",
            "_width": "0.127",
            "_layer": "51"
          },
          {
            "_x1": "0.126959",
            "_y1": "0.506441",
            "_x2": "0.0423188",
            "_y2": "0.739191",
            "_width": "0.127",
            "_layer": "51"
          },
          {
            "_x1": "0.296231",
            "_y1": "0.294841",
            "_x2": "0.126959",
            "_y2": "0.506441",
            "_width": "0.127",
            "_layer": "51"
          },
          {
            "_x1": "0.507819",
            "_y1": "0.125569",
            "_x2": "0.296231",
            "_y2": "0.294841",
            "_width": "0.127",
            "_layer": "51"
          },
          {
            "_x1": "0.740569",
            "_y1": "0.0409313",
            "_x2": "0.507819",
            "_y2": "0.125569",
            "_width": "0.127",
            "_layer": "51"
          },
          {
            "_x1": "0.994481",
            "_y1": "-0.00138125",
            "_x2": "0.740569",
            "_y2": "0.0409313",
            "_width": "0.127",
            "_layer": "51"
          },
          {
            "_x1": "65.001",
            "_y1": "-0.00138125",
            "_x2": "0.994481",
            "_y2": "-0.00138125",
            "_width": "0.127",
            "_layer": "51"
          },
          {
            "_x1": "65.2549",
            "_y1": "0.0409313",
            "_x2": "65.001",
            "_y2": "-0.00138125",
            "_width": "0.127",
            "_layer": "51"
          },
          {
            "_x1": "65.4877",
            "_y1": "0.125569",
            "_x2": "65.2549",
            "_y2": "0.0409313",
            "_width": "0.127",
            "_layer": "51"
          },
          {
            "_x1": "65.6993",
            "_y1": "0.294841",
            "_x2": "65.4877",
            "_y2": "0.125569",
            "_width": "0.127",
            "_layer": "51"
          },
          {
            "_x1": "65.8686",
            "_y1": "0.506441",
            "_x2": "65.6993",
            "_y2": "0.294841",
            "_width": "0.127",
            "_layer": "51"
          },
          {
            "_x1": "65.9532",
            "_y1": "0.739191",
            "_x2": "65.8686",
            "_y2": "0.506441",
            "_width": "0.127",
            "_layer": "51"
          },
          {
            "_x1": "65.9955",
            "_y1": "0.9931",
            "_x2": "65.9532",
            "_y2": "0.739191",
            "_width": "0.127",
            "_layer": "51"
          },
          {
            "_x1": "65.9955",
            "_y1": "2.53772",
            "_x2": "65.9955",
            "_y2": "0.9931",
            "_width": "0.127",
            "_layer": "51"
          },
          {
            "_x1": "68.5346",
            "_y1": "5.07682",
            "_x2": "65.9955",
            "_y2": "2.53772",
            "_width": "0.127",
            "_layer": "51"
          },
          {
            "_x1": "68.5346",
            "_y1": "37.8101",
            "_x2": "68.5346",
            "_y2": "5.07682",
            "_width": "0.127",
            "_layer": "51"
          },
          {
            "_x1": "65.9955",
            "_y1": "40.3492",
            "_x2": "68.5346",
            "_y2": "37.8101",
            "_width": "0.127",
            "_layer": "51"
          },
          {
            "_x1": "65.9955",
            "_y1": "51.7751",
            "_x2": "65.9955",
            "_y2": "40.3492",
            "_width": "0.127",
            "_layer": "51"
          },
          {
            "_x1": "64.472",
            "_y1": "53.2986",
            "_x2": "65.9955",
            "_y2": "51.7751",
            "_width": "0.127",
            "_layer": "51"
          },
          {
            "_x1": "0.994481",
            "_y1": "53.2986",
            "_x2": "64.472",
            "_y2": "53.2986",
            "_width": "0.127",
            "_layer": "21"
          },
          {
            "_x1": "0.740569",
            "_y1": "53.2563",
            "_x2": "0.994481",
            "_y2": "53.2986",
            "_width": "0.127",
            "_layer": "21"
          },
          {
            "_x1": "0.507819",
            "_y1": "53.1505",
            "_x2": "0.740569",
            "_y2": "53.2563",
            "_width": "0.127",
            "_layer": "21"
          },
          {
            "_x1": "0.296231",
            "_y1": "53.0024",
            "_x2": "0.507819",
            "_y2": "53.1505",
            "_width": "0.127",
            "_layer": "21"
          },
          {
            "_x1": "0.126959",
            "_y1": "52.7908",
            "_x2": "0.296231",
            "_y2": "53.0024",
            "_width": "0.127",
            "_layer": "21"
          },
          {
            "_x1": "0.0423188",
            "_y1": "52.558",
            "_x2": "0.126959",
            "_y2": "52.7908",
            "_width": "0.127",
            "_layer": "21"
          },
          {
            "_x1": "0",
            "_y1": "52.283",
            "_x2": "0.0423188",
            "_y2": "52.558",
            "_width": "0.127",
            "_layer": "21"
          },
          {
            "_x1": "0",
            "_y1": "0.9931",
            "_x2": "0",
            "_y2": "52.283",
            "_width": "0.127",
            "_layer": "21"
          },
          {
            "_x1": "0.0423188",
            "_y1": "0.739191",
            "_x2": "0",
            "_y2": "0.9931",
            "_width": "0.127",
            "_layer": "21"
          },
          {
            "_x1": "0.126959",
            "_y1": "0.506441",
            "_x2": "0.0423188",
            "_y2": "0.739191",
            "_width": "0.127",
            "_layer": "21"
          },
          {
            "_x1": "0.296231",
            "_y1": "0.294841",
            "_x2": "0.126959",
            "_y2": "0.506441",
            "_width": "0.127",
            "_layer": "21"
          },
          {
            "_x1": "0.507819",
            "_y1": "0.125569",
            "_x2": "0.296231",
            "_y2": "0.294841",
            "_width": "0.127",
            "_layer": "21"
          },
          {
            "_x1": "0.740569",
            "_y1": "0.0409313",
            "_x2": "0.507819",
            "_y2": "0.125569",
            "_width": "0.127",
            "_layer": "21"
          },
          {
            "_x1": "0.994481",
            "_y1": "-0.00138125",
            "_x2": "0.740569",
            "_y2": "0.0409313",
            "_width": "0.127",
            "_layer": "21"
          },
          {
            "_x1": "65.001",
            "_y1": "-0.00138125",
            "_x2": "0.994481",
            "_y2": "-0.00138125",
            "_width": "0.127",
            "_layer": "21"
          },
          {
            "_x1": "65.2549",
            "_y1": "0.0409313",
            "_x2": "65.001",
            "_y2": "-0.00138125",
            "_width": "0.127",
            "_layer": "21"
          },
          {
            "_x1": "65.4877",
            "_y1": "0.125569",
            "_x2": "65.2549",
            "_y2": "0.0409313",
            "_width": "0.127",
            "_layer": "21"
          },
          {
            "_x1": "65.6993",
            "_y1": "0.294841",
            "_x2": "65.4877",
            "_y2": "0.125569",
            "_width": "0.127",
            "_layer": "21"
          },
          {
            "_x1": "65.8686",
            "_y1": "0.506441",
            "_x2": "65.6993",
            "_y2": "0.294841",
            "_width": "0.127",
            "_layer": "21"
          },
          {
            "_x1": "65.9532",
            "_y1": "0.739191",
            "_x2": "65.8686",
            "_y2": "0.506441",
            "_width": "0.127",
            "_layer": "21"
          },
          {
            "_x1": "65.9955",
            "_y1": "0.9931",
            "_x2": "65.9532",
            "_y2": "0.739191",
            "_width": "0.127",
            "_layer": "21"
          },
          {
            "_x1": "65.9955",
            "_y1": "2.53772",
            "_x2": "65.9955",
            "_y2": "0.9931",
            "_width": "0.127",
            "_layer": "21"
          },
          {
            "_x1": "68.5346",
            "_y1": "5.07682",
            "_x2": "65.9955",
            "_y2": "2.53772",
            "_width": "0.127",
            "_layer": "21"
          },
          {
            "_x1": "68.5346",
            "_y1": "37.8101",
            "_x2": "68.5346",
            "_y2": "5.07682",
            "_width": "0.127",
            "_layer": "21"
          },
          {
            "_x1": "65.9955",
            "_y1": "40.3492",
            "_x2": "68.5346",
            "_y2": "37.8101",
            "_width": "0.127",
            "_layer": "21"
          },
          {
            "_x1": "65.9955",
            "_y1": "51.7751",
            "_x2": "65.9955",
            "_y2": "40.3492",
            "_width": "0.127",
            "_layer": "21"
          },
          {
            "_x1": "64.472",
            "_y1": "53.2986",
            "_x2": "65.9955",
            "_y2": "51.7751",
            "_width": "0.127",
            "_layer": "21"
          },
          {
            "_x1": "0.0462313",
            "_y1": "53.2524",
            "_x2": "0.257819",
            "_y2": "53.4005",
            "_width": "0.05",
            "_layer": "39"
          },
          {
            "_x1": "-0.123041",
            "_y1": "53.0408",
            "_x2": "0.0462313",
            "_y2": "53.2524",
            "_width": "0.05",
            "_layer": "39"
          },
          {
            "_x1": "-0.207681",
            "_y1": "52.808",
            "_x2": "-0.123041",
            "_y2": "53.0408",
            "_width": "0.05",
            "_layer": "39"
          },
          {
            "_x1": "-0.25",
            "_y1": "52.533",
            "_x2": "-0.207681",
            "_y2": "52.808",
            "_width": "0.05",
            "_layer": "39"
          },
          {
            "_x1": "-0.25",
            "_y1": "0.9931",
            "_x2": "-0.25",
            "_y2": "1",
            "_width": "0.05",
            "_layer": "39"
          },
          {
            "_x1": "-0.25",
            "_y1": "1",
            "_x2": "-0.25",
            "_y2": "52.533",
            "_width": "0.05",
            "_layer": "39"
          },
          {
            "_x1": "0.257819",
            "_y1": "53.4005",
            "_x2": "0.490569",
            "_y2": "53.5063",
            "_width": "0.05",
            "_layer": "39"
          },
          {
            "_x1": "0.490569",
            "_y1": "53.5063",
            "_x2": "0.744481",
            "_y2": "53.5486",
            "_width": "0.05",
            "_layer": "39"
          },
          {
            "_x1": "0.744481",
            "_y1": "53.5486",
            "_x2": "64.722",
            "_y2": "53.5486",
            "_width": "0.05",
            "_layer": "39"
          },
          {
            "_x1": "64.722",
            "_y1": "53.5486",
            "_x2": "66.2455",
            "_y2": "52.0251",
            "_width": "0.05",
            "_layer": "39"
          },
          {
            "_x1": "66.2455",
            "_y1": "52.0251",
            "_x2": "66.2455",
            "_y2": "40.5992",
            "_width": "0.05",
            "_layer": "39"
          },
          {
            "_x1": "66.2455",
            "_y1": "40.5992",
            "_x2": "68.7846",
            "_y2": "38.0601",
            "_width": "0.05",
            "_layer": "39"
          },
          {
            "_x1": "68.7846",
            "_y1": "38.0601",
            "_x2": "68.7846",
            "_y2": "4.82682",
            "_width": "0.05",
            "_layer": "39"
          },
          {
            "_x1": "68.7846",
            "_y1": "4.82682",
            "_x2": "66.2455",
            "_y2": "2.28772",
            "_width": "0.05",
            "_layer": "39"
          },
          {
            "_x1": "65.001",
            "_y1": "-0.251381",
            "_x2": "0.744481",
            "_y2": "-0.251381",
            "_width": "0.05",
            "_layer": "39"
          },
          {
            "_x1": "66.2455",
            "_y1": "2.28772",
            "_x2": "66.2455",
            "_y2": "0.9931",
            "_width": "0.05",
            "_layer": "39"
          },
          {
            "_x1": "0.75",
            "_y1": "-0.25",
            "_x2": "-0.25",
            "_y2": "1",
            "_width": "0.05",
            "_layer": "39",
            "_curve": "-85"
          },
          {
            "_x1": "65",
            "_y1": "-0.25",
            "_x2": "66.25",
            "_y2": "1",
            "_width": "0.05",
            "_layer": "39",
            "_curve": "85"
          }
        ],
        "pad": [
          {
            "_name": "3V3",
            "_x": "35.56",
            "_y": "2.54",
            "_drill": "1.016",
            "_diameter": "1.6764"
          },
          {
            "_name": "5V",
            "_x": "38.1",
            "_y": "2.54",
            "_drill": "1.016",
            "_diameter": "1.6764"
          },
          {
            "_name": "A0",
            "_x": "50.8",
            "_y": "2.54",
            "_drill": "1.016",
            "_diameter": "1.6764",
            "_shape": "square"
          },
          {
            "_name": "A1",
            "_x": "53.34",
            "_y": "2.54",
            "_drill": "1.016",
            "_diameter": "1.6764"
          },
          {
            "_name": "A2",
            "_x": "55.88",
            "_y": "2.54",
            "_drill": "1.016",
            "_diameter": "1.6764"
          },
          {
            "_name": "A3",
            "_x": "58.42",
            "_y": "2.54",
            "_drill": "1.016",
            "_diameter": "1.6764"
          },
          {
            "_name": "A4",
            "_x": "60.96",
            "_y": "2.54",
            "_drill": "1.016",
            "_diameter": "1.6764"
          },
          {
            "_name": "A5",
            "_x": "63.5",
            "_y": "2.54",
            "_drill": "1.016",
            "_diameter": "1.6764"
          },
          {
            "_name": "AREF",
            "_x": "23.876",
            "_y": "50.8",
            "_drill": "1.016",
            "_diameter": "1.6764",
            "_rot": "R180"
          },
          {
            "_name": "D0",
            "_x": "63.5",
            "_y": "50.8",
            "_drill": "1.016",
            "_diameter": "1.6764",
            "_shape": "square",
            "_rot": "R180"
          },
          {
            "_name": "D1",
            "_x": "60.96",
            "_y": "50.8",
            "_drill": "1.016",
            "_diameter": "1.6764",
            "_rot": "R180"
          },
          {
            "_name": "D2",
            "_x": "58.42",
            "_y": "50.8",
            "_drill": "1.016",
            "_diameter": "1.6764",
            "_rot": "R180"
          },
          {
            "_name": "D3",
            "_x": "55.88",
            "_y": "50.8",
            "_drill": "1.016",
            "_diameter": "1.6764",
            "_rot": "R180"
          },
          {
            "_name": "D4",
            "_x": "53.34",
            "_y": "50.8",
            "_drill": "1.016",
            "_diameter": "1.6764",
            "_rot": "R180"
          },
          {
            "_name": "D5",
            "_x": "50.8",
            "_y": "50.8",
            "_drill": "1.016",
            "_diameter": "1.6764",
            "_rot": "R180"
          },
          {
            "_name": "D6",
            "_x": "48.26",
            "_y": "50.8",
            "_drill": "1.016",
            "_diameter": "1.6764",
            "_rot": "R180"
          },
          {
            "_name": "D7",
            "_x": "45.72",
            "_y": "50.8",
            "_drill": "1.016",
            "_diameter": "1.6764",
            "_rot": "R180"
          },
          {
            "_name": "D8",
            "_x": "41.656",
            "_y": "50.8",
            "_drill": "1.016",
            "_diameter": "1.6764",
            "_shape": "square",
            "_rot": "R180"
          },
          {
            "_name": "D9",
            "_x": "39.116",
            "_y": "50.8",
            "_drill": "1.016",
            "_diameter": "1.6764",
            "_rot": "R180"
          },
          {
            "_name": "D10",
            "_x": "36.576",
            "_y": "50.8",
            "_drill": "1.016",
            "_diameter": "1.6764",
            "_rot": "R180"
          },
          {
            "_name": "D11",
            "_x": "34.036",
            "_y": "50.8",
            "_drill": "1.016",
            "_diameter": "1.6764",
            "_rot": "R180"
          },
          {
            "_name": "D12",
            "_x": "31.496",
            "_y": "50.8",
            "_drill": "1.016",
            "_diameter": "1.6764",
            "_rot": "R180"
          },
          {
            "_name": "D13",
            "_x": "28.956",
            "_y": "50.8",
            "_drill": "1.016",
            "_diameter": "1.6764",
            "_rot": "R180"
          },
          {
            "_name": "GND_2",
            "_x": "40.64",
            "_y": "2.54",
            "_drill": "1.016",
            "_diameter": "1.6764"
          },
          {
            "_name": "GND_1",
            "_x": "43.18",
            "_y": "2.54",
            "_drill": "1.016",
            "_diameter": "1.6764"
          },
          {
            "_name": "GND_3",
            "_x": "26.416",
            "_y": "50.8",
            "_drill": "1.016",
            "_diameter": "1.6764",
            "_rot": "R180"
          },
          {
            "_name": "RST",
            "_x": "33.02",
            "_y": "2.54",
            "_drill": "1.016",
            "_diameter": "1.6764"
          },
          {
            "_name": "VIN",
            "_x": "45.72",
            "_y": "2.54",
            "_drill": "1.016",
            "_diameter": "1.6764"
          },
          {
            "_name": "A4(SDA)",
            "_x": "21.336",
            "_y": "50.8",
            "_drill": "1.016",
            "_diameter": "1.6764",
            "_rot": "R180"
          },
          {
            "_name": "A5(SCL)",
            "_x": "18.796",
            "_y": "50.8",
            "_drill": "1.016",
            "_diameter": "1.6764",
            "_rot": "R180"
          },
          {
            "_name": "IOREF",
            "_x": "30.48",
            "_y": "2.54",
            "_drill": "1.016",
            "_diameter": "1.6764"
          },
          {
            "_name": "P1",
            "_x": "27.94",
            "_y": "2.54",
            "_drill": "1.016",
            "_diameter": "1.6764",
            "_shape": "square"
          }
        ],
        "hole": [
          {
            "_x": "66.04",
            "_y": "35.56",
            "_drill": "3.3"
          },
          {
            "_x": "66.04",
            "_y": "7.62",
            "_drill": "3.3"
          },
          {
            "_x": "15.24",
            "_y": "50.8",
            "_drill": "3.3"
          },
          {
            "_x": "13.97",
            "_y": "2.54",
            "_drill": "3.3"
          }
        ],
        "_name": "Arduino Uno R3"
      },
      {
        "wire": [
          {
            "_x1": "-26.67",
            "_y1": "50.8",
            "_x2": "-23.37",
            "_y2": "50.8",
            "_width": "0.127",
            "_layer": "21"
          },
          {
            "_x1": "-23.37",
            "_y1": "50.8",
            "_x2": "-14.378",
            "_y2": "50.8",
            "_width": "0.127",
            "_layer": "21"
          },
          {
            "_x1": "-14.378",
            "_y1": "50.8",
            "_x2": "2.22",
            "_y2": "50.8",
            "_width": "0.127",
            "_layer": "21"
          },
          {
            "_x1": "2.22",
            "_y1": "50.8",
            "_x2": "14.02",
            "_y2": "50.8",
            "_width": "0.127",
            "_layer": "21"
          },
          {
            "_x1": "14.02",
            "_y1": "50.8",
            "_x2": "26.67",
            "_y2": "50.8",
            "_width": "0.127",
            "_layer": "21"
          },
          {
            "_x1": "26.67",
            "_y1": "50.8",
            "_x2": "26.67",
            "_y2": "-50.8",
            "_width": "0.127",
            "_layer": "21"
          },
          {
            "_x1": "26.67",
            "_y1": "-50.8",
            "_x2": "-26.67",
            "_y2": "-50.8",
            "_width": "0.127",
            "_layer": "21"
          },
          {
            "_x1": "-26.67",
            "_y1": "-50.8",
            "_x2": "-26.67",
            "_y2": "50.8",
            "_width": "0.127",
            "_layer": "21"
          },
          {
            "_x1": "14.02",
            "_y1": "50.8",
            "_x2": "14.02",
            "_y2": "57.15",
            "_width": "0.127",
            "_layer": "21"
          },
          {
            "_x1": "14.02",
            "_y1": "57.15",
            "_x2": "2.22",
            "_y2": "57.15",
            "_width": "0.127",
            "_layer": "21"
          },
          {
            "_x1": "2.22",
            "_y1": "57.15",
            "_x2": "2.22",
            "_y2": "50.8",
            "_width": "0.127",
            "_layer": "21"
          },
          {
            "_x1": "-23.37",
            "_y1": "50.8",
            "_x2": "-23.37",
            "_y2": "52.61",
            "_width": "0.127",
            "_layer": "21"
          },
          {
            "_x1": "-23.37",
            "_y1": "52.61",
            "_x2": "-14.378",
            "_y2": "52.61",
            "_width": "0.127",
            "_layer": "21"
          },
          {
            "_x1": "-14.378",
            "_y1": "52.61",
            "_x2": "-14.378",
            "_y2": "50.8",
            "_width": "0.127",
            "_layer": "21"
          },
          {
            "_x1": "-26.92",
            "_y1": "51.05",
            "_x2": "-23.62",
            "_y2": "51.05",
            "_width": "0.05",
            "_layer": "39"
          },
          {
            "_x1": "-23.62",
            "_y1": "51.05",
            "_x2": "-23.62",
            "_y2": "52.86",
            "_width": "0.05",
            "_layer": "39"
          },
          {
            "_x1": "-23.62",
            "_y1": "52.86",
            "_x2": "-14.128",
            "_y2": "52.86",
            "_width": "0.05",
            "_layer": "39"
          },
          {
            "_x1": "-14.128",
            "_y1": "52.86",
            "_x2": "-14.128",
            "_y2": "51.05",
            "_width": "0.05",
            "_layer": "39"
          },
          {
            "_x1": "-14.128",
            "_y1": "51.05",
            "_x2": "1.97",
            "_y2": "51.05",
            "_width": "0.05",
            "_layer": "39"
          },
          {
            "_x1": "1.97",
            "_y1": "51.05",
            "_x2": "1.97",
            "_y2": "57.4",
            "_width": "0.05",
            "_layer": "39"
          },
          {
            "_x1": "1.97",
            "_y1": "57.4",
            "_x2": "14.27",
            "_y2": "57.4",
            "_width": "0.05",
            "_layer": "39"
          },
          {
            "_x1": "14.27",
            "_y1": "57.4",
            "_x2": "14.27",
            "_y2": "51.05",
            "_width": "0.05",
            "_layer": "39"
          },
          {
            "_x1": "14.27",
            "_y1": "51.05",
            "_x2": "26.92",
            "_y2": "51.05",
            "_width": "0.05",
            "_layer": "39"
          },
          {
            "_x1": "26.92",
            "_y1": "51.05",
            "_x2": "26.92",
            "_y2": "-51.05",
            "_width": "0.05",
            "_layer": "39"
          },
          {
            "_x1": "26.92",
            "_y1": "-51.05",
            "_x2": "-26.92",
            "_y2": "-51.05",
            "_width": "0.05",
            "_layer": "39"
          },
          {
            "_x1": "-26.92",
            "_y1": "-51.05",
            "_x2": "-26.92",
            "_y2": "51.05",
            "_width": "0.05",
            "_layer": "39"
          },
          {
            "_x1": "-26.67",
            "_y1": "50.8",
            "_x2": "-23.37",
            "_y2": "50.8",
            "_width": "0.127",
            "_layer": "51"
          },
          {
            "_x1": "-23.37",
            "_y1": "50.8",
            "_x2": "-14.378",
            "_y2": "50.8",
            "_width": "0.127",
            "_layer": "51"
          },
          {
            "_x1": "-14.378",
            "_y1": "50.8",
            "_x2": "2.22",
            "_y2": "50.8",
            "_width": "0.127",
            "_layer": "51"
          },
          {
            "_x1": "2.22",
            "_y1": "50.8",
            "_x2": "14.02",
            "_y2": "50.8",
            "_width": "0.127",
            "_layer": "51"
          },
          {
            "_x1": "14.02",
            "_y1": "50.8",
            "_x2": "26.67",
            "_y2": "50.8",
            "_width": "0.127",
            "_layer": "51"
          },
          {
            "_x1": "26.67",
            "_y1": "50.8",
            "_x2": "26.67",
            "_y2": "-50.8",
            "_width": "0.127",
            "_layer": "51"
          },
          {
            "_x1": "26.67",
            "_y1": "-50.8",
            "_x2": "-26.67",
            "_y2": "-50.8",
            "_width": "0.127",
            "_layer": "51"
          },
          {
            "_x1": "-26.67",
            "_y1": "-50.8",
            "_x2": "-26.67",
            "_y2": "50.8",
            "_width": "0.127",
            "_layer": "51"
          },
          {
            "_x1": "14.02",
            "_y1": "50.8",
            "_x2": "14.02",
            "_y2": "57.15",
            "_width": "0.127",
            "_layer": "51"
          },
          {
            "_x1": "14.02",
            "_y1": "57.15",
            "_x2": "2.22",
            "_y2": "57.15",
            "_width": "0.127",
            "_layer": "51"
          },
          {
            "_x1": "2.22",
            "_y1": "57.15",
            "_x2": "2.22",
            "_y2": "50.8",
            "_width": "0.127",
            "_layer": "51"
          },
          {
            "_x1": "-23.37",
            "_y1": "50.8",
            "_x2": "-23.37",
            "_y2": "52.61",
            "_width": "0.127",
            "_layer": "51"
          },
          {
            "_x1": "-23.37",
            "_y1": "52.61",
            "_x2": "-14.378",
            "_y2": "52.61",
            "_width": "0.127",
            "_layer": "51"
          },
          {
            "_x1": "-14.378",
            "_y1": "52.61",
            "_x2": "-14.378",
            "_y2": "50.8",
            "_width": "0.127",
            "_layer": "51"
          }
        ],
        "text": [
          {
            "_x": "-26.7",
            "_y": "53.31",
            "_size": "1.27",
            "_layer": "25",
            "__text": ">NAME"
          },
          {
            "_x": "-26.7",
            "_y": "-52.71",
            "_size": "1.27",
            "_layer": "27",
            "__text": ">VALUE"
          }
        ],
        "pad": [
          {
            "_name": "NC",
            "_x": "-24.13",
            "_y": "22.86",
            "_drill": "0.85",
            "_shape": "square"
          },
          {
            "_name": "IOREF",
            "_x": "-24.13",
            "_y": "20.32",
            "_drill": "0.85"
          },
          {
            "_name": "RESET",
            "_x": "-24.13",
            "_y": "17.78",
            "_drill": "0.85"
          },
          {
            "_name": "3V3",
            "_x": "-24.13",
            "_y": "15.24",
            "_drill": "0.85"
          },
          {
            "_name": "5V_1",
            "_x": "-24.13",
            "_y": "12.7",
            "_drill": "0.85"
          },
          {
            "_name": "GND1",
            "_x": "-24.13",
            "_y": "10.16",
            "_drill": "0.85"
          },
          {
            "_name": "GND2",
            "_x": "-24.13",
            "_y": "7.62",
            "_drill": "0.85"
          },
          {
            "_name": "VIN",
            "_x": "-24.13",
            "_y": "5.08",
            "_drill": "0.85"
          },
          {
            "_name": "AD0",
            "_x": "-24.13",
            "_y": "0",
            "_drill": "0.85"
          },
          {
            "_name": "AD1",
            "_x": "-24.13",
            "_y": "-2.54",
            "_drill": "0.85"
          },
          {
            "_name": "AD2",
            "_x": "-24.13",
            "_y": "-5.08",
            "_drill": "0.85"
          },
          {
            "_name": "AD3",
            "_x": "-24.13",
            "_y": "-7.62",
            "_drill": "0.85"
          },
          {
            "_name": "AD4",
            "_x": "-24.13",
            "_y": "-10.16",
            "_drill": "0.85"
          },
          {
            "_name": "AD5",
            "_x": "-24.13",
            "_y": "-12.7",
            "_drill": "0.85"
          },
          {
            "_name": "AD6",
            "_x": "-24.13",
            "_y": "-15.24",
            "_drill": "0.85"
          },
          {
            "_name": "AD7",
            "_x": "-24.13",
            "_y": "-17.78",
            "_drill": "0.85"
          },
          {
            "_name": "AD8",
            "_x": "-24.13",
            "_y": "-22.86",
            "_drill": "0.85"
          },
          {
            "_name": "AD9",
            "_x": "-24.13",
            "_y": "-25.4",
            "_drill": "0.85"
          },
          {
            "_name": "AD10",
            "_x": "-24.13",
            "_y": "-27.94",
            "_drill": "0.85"
          },
          {
            "_name": "AD11",
            "_x": "-24.13",
            "_y": "-30.48",
            "_drill": "0.85"
          },
          {
            "_name": "AD12",
            "_x": "-24.13",
            "_y": "-33.02",
            "_drill": "0.85"
          },
          {
            "_name": "AD13",
            "_x": "-24.13",
            "_y": "-35.56",
            "_drill": "0.85"
          },
          {
            "_name": "AD14",
            "_x": "-24.13",
            "_y": "-37.846",
            "_drill": "0.85"
          },
          {
            "_name": "AD15",
            "_x": "-24.13",
            "_y": "-40.386",
            "_drill": "0.85"
          },
          {
            "_name": "GND5",
            "_x": "-19.05",
            "_y": "-45.72",
            "_drill": "0.85"
          },
          {
            "_name": "GND4",
            "_x": "-19.05",
            "_y": "-43.18",
            "_drill": "0.85"
          },
          {
            "_name": "53",
            "_x": "-16.51",
            "_y": "-45.72",
            "_drill": "0.85"
          },
          {
            "_name": "52",
            "_x": "-16.51",
            "_y": "-43.18",
            "_drill": "0.85"
          },
          {
            "_name": "51",
            "_x": "-13.97",
            "_y": "-45.72",
            "_drill": "0.85"
          },
          {
            "_name": "50",
            "_x": "-13.97",
            "_y": "-43.18",
            "_drill": "0.85"
          },
          {
            "_name": "49",
            "_x": "-11.43",
            "_y": "-45.72",
            "_drill": "0.85"
          },
          {
            "_name": "48",
            "_x": "-11.43",
            "_y": "-43.18",
            "_drill": "0.85"
          },
          {
            "_name": "46",
            "_x": "-8.89",
            "_y": "-43.18",
            "_drill": "0.85"
          },
          {
            "_name": "47",
            "_x": "-8.89",
            "_y": "-45.72",
            "_drill": "0.85"
          },
          {
            "_name": "44",
            "_x": "-6.35",
            "_y": "-43.18",
            "_drill": "0.85"
          },
          {
            "_name": "45",
            "_x": "-6.35",
            "_y": "-45.72",
            "_drill": "0.85"
          },
          {
            "_name": "42",
            "_x": "-3.81",
            "_y": "-43.18",
            "_drill": "0.85"
          },
          {
            "_name": "43",
            "_x": "-3.81",
            "_y": "-45.72",
            "_drill": "0.85"
          },
          {
            "_name": "40",
            "_x": "-1.27",
            "_y": "-43.18",
            "_drill": "0.85"
          },
          {
            "_name": "41",
            "_x": "-1.27",
            "_y": "-45.72",
            "_drill": "0.85"
          },
          {
            "_name": "38",
            "_x": "1.27",
            "_y": "-43.18",
            "_drill": "0.85"
          },
          {
            "_name": "39",
            "_x": "1.27",
            "_y": "-45.72",
            "_drill": "0.85"
          },
          {
            "_name": "36",
            "_x": "3.81",
            "_y": "-43.18",
            "_drill": "0.85"
          },
          {
            "_name": "37",
            "_x": "3.81",
            "_y": "-45.72",
            "_drill": "0.85"
          },
          {
            "_name": "34",
            "_x": "6.35",
            "_y": "-43.18",
            "_drill": "0.85"
          },
          {
            "_name": "35",
            "_x": "6.35",
            "_y": "-45.72",
            "_drill": "0.85"
          },
          {
            "_name": "32",
            "_x": "8.89",
            "_y": "-43.18",
            "_drill": "0.85"
          },
          {
            "_name": "33",
            "_x": "8.89",
            "_y": "-45.72",
            "_drill": "0.85"
          },
          {
            "_name": "30",
            "_x": "11.43",
            "_y": "-43.18",
            "_drill": "0.85"
          },
          {
            "_name": "31",
            "_x": "11.43",
            "_y": "-45.72",
            "_drill": "0.85"
          },
          {
            "_name": "28",
            "_x": "13.97",
            "_y": "-43.18",
            "_drill": "0.85"
          },
          {
            "_name": "29",
            "_x": "13.97",
            "_y": "-45.72",
            "_drill": "0.85"
          },
          {
            "_name": "26",
            "_x": "16.51",
            "_y": "-43.18",
            "_drill": "0.85"
          },
          {
            "_name": "27",
            "_x": "16.51",
            "_y": "-45.72",
            "_drill": "0.85"
          },
          {
            "_name": "24",
            "_x": "19.05",
            "_y": "-43.18",
            "_drill": "0.85"
          },
          {
            "_name": "25",
            "_x": "19.05",
            "_y": "-45.72",
            "_drill": "0.85"
          },
          {
            "_name": "22",
            "_x": "21.59",
            "_y": "-43.18",
            "_drill": "0.85"
          },
          {
            "_name": "23",
            "_x": "21.59",
            "_y": "-45.72",
            "_drill": "0.85"
          },
          {
            "_name": "5V_2",
            "_x": "24.13",
            "_y": "-43.18",
            "_drill": "0.85"
          },
          {
            "_name": "5V_3",
            "_x": "24.13",
            "_y": "-45.72",
            "_drill": "0.85"
          },
          {
            "_name": "21",
            "_x": "24.13",
            "_y": "-35.56",
            "_drill": "0.85"
          },
          {
            "_name": "20",
            "_x": "24.13",
            "_y": "-33.02",
            "_drill": "0.85"
          },
          {
            "_name": "19",
            "_x": "24.13",
            "_y": "-30.48",
            "_drill": "0.85"
          },
          {
            "_name": "18",
            "_x": "24.13",
            "_y": "-27.94",
            "_drill": "0.85"
          },
          {
            "_name": "17",
            "_x": "24.13",
            "_y": "-25.4",
            "_drill": "0.85"
          },
          {
            "_name": "16",
            "_x": "24.13",
            "_y": "-22.86",
            "_drill": "0.85"
          },
          {
            "_name": "15",
            "_x": "24.13",
            "_y": "-20.32",
            "_drill": "0.85"
          },
          {
            "_name": "14",
            "_x": "24.13",
            "_y": "-17.78",
            "_drill": "0.85"
          },
          {
            "_name": "0",
            "_x": "24.13",
            "_y": "-12.7",
            "_drill": "0.85"
          },
          {
            "_name": "1",
            "_x": "24.13",
            "_y": "-10.16",
            "_drill": "0.85"
          },
          {
            "_name": "2",
            "_x": "24.13",
            "_y": "-7.62",
            "_drill": "0.85"
          },
          {
            "_name": "3",
            "_x": "24.13",
            "_y": "-5.08",
            "_drill": "0.85"
          },
          {
            "_name": "4",
            "_x": "24.13",
            "_y": "-2.54",
            "_drill": "0.85"
          },
          {
            "_name": "5",
            "_x": "24.13",
            "_y": "0",
            "_drill": "0.85"
          },
          {
            "_name": "6",
            "_x": "24.13",
            "_y": "2.54",
            "_drill": "0.85"
          },
          {
            "_name": "7",
            "_x": "24.13",
            "_y": "5.08",
            "_drill": "0.85"
          },
          {
            "_name": "8",
            "_x": "24.13",
            "_y": "9.144",
            "_drill": "0.85"
          },
          {
            "_name": "9",
            "_x": "24.13",
            "_y": "11.684",
            "_drill": "0.85"
          },
          {
            "_name": "10",
            "_x": "24.13",
            "_y": "14.224",
            "_drill": "0.85"
          },
          {
            "_name": "11",
            "_x": "24.13",
            "_y": "16.764",
            "_drill": "0.85"
          },
          {
            "_name": "12",
            "_x": "24.13",
            "_y": "19.304",
            "_drill": "0.85"
          },
          {
            "_name": "13",
            "_x": "24.13",
            "_y": "21.844",
            "_drill": "0.85"
          },
          {
            "_name": "GND3",
            "_x": "24.13",
            "_y": "24.384",
            "_drill": "0.85"
          },
          {
            "_name": "AREF",
            "_x": "24.13",
            "_y": "26.924",
            "_drill": "0.85"
          },
          {
            "_name": "SDA",
            "_x": "24.13",
            "_y": "29.464",
            "_drill": "0.85"
          },
          {
            "_name": "SCL",
            "_x": "24.13",
            "_y": "32.004",
            "_drill": "0.85"
          }
        ],
        "hole": [
          {
            "_x": "-24.13",
            "_y": "36.83",
            "_drill": "3.2"
          },
          {
            "_x": "-19.05",
            "_y": "-15.24",
            "_drill": "3.2"
          },
          {
            "_x": "8.89",
            "_y": "-15.24",
            "_drill": "3.2"
          },
          {
            "_x": "24.13",
            "_y": "35.56",
            "_drill": "3.2"
          },
          {
            "_x": "-24.13",
            "_y": "-45.72",
            "_drill": "3.2"
          },
          {
            "_x": "24.13",
            "_y": "-39.37",
            "_drill": "3.2"
          }
        ],
        "_name": "Arduino Mega 2560"
      },
      {
        "wire": [
          {
            "_x1": "-8.89",
            "_y1": "21.59",
            "_x2": "8.89",
            "_y2": "21.59",
            "_width": "0.127",
            "_layer": "51"
          },
          {
            "_x1": "8.89",
            "_y1": "21.59",
            "_x2": "8.89",
            "_y2": "-21.59",
            "_width": "0.127",
            "_layer": "51"
          },
          {
            "_x1": "8.89",
            "_y1": "-21.59",
            "_x2": "3",
            "_y2": "-21.59",
            "_width": "0.127",
            "_layer": "51"
          },
          {
            "_x1": "3",
            "_y1": "-21.59",
            "_x2": "-2.97",
            "_y2": "-21.59",
            "_width": "0.127",
            "_layer": "51"
          },
          {
            "_x1": "-2.97",
            "_y1": "-21.59",
            "_x2": "-8.89",
            "_y2": "-21.59",
            "_width": "0.127",
            "_layer": "51"
          },
          {
            "_x1": "-8.89",
            "_y1": "-21.59",
            "_x2": "-8.89",
            "_y2": "21.59",
            "_width": "0.127",
            "_layer": "51"
          },
          {
            "_x1": "-8.89",
            "_y1": "21.59",
            "_x2": "8.89",
            "_y2": "21.59",
            "_width": "0.127",
            "_layer": "21"
          },
          {
            "_x1": "8.89",
            "_y1": "21.59",
            "_x2": "8.89",
            "_y2": "-21.59",
            "_width": "0.127",
            "_layer": "21"
          },
          {
            "_x1": "8.89",
            "_y1": "-21.59",
            "_x2": "-8.89",
            "_y2": "-21.59",
            "_width": "0.127",
            "_layer": "21"
          },
          {
            "_x1": "-8.89",
            "_y1": "-21.59",
            "_x2": "-8.89",
            "_y2": "21.59",
            "_width": "0.127",
            "_layer": "21"
          },
          {
            "_x1": "-9.14",
            "_y1": "21.84",
            "_x2": "9.14",
            "_y2": "21.84",
            "_width": "0.05",
            "_layer": "39"
          },
          {
            "_x1": "9.14",
            "_y1": "21.84",
            "_x2": "9.14",
            "_y2": "-21.84",
            "_width": "0.05",
            "_layer": "39"
          },
          {
            "_x1": "-9.14",
            "_y1": "-21.84",
            "_x2": "-9.14",
            "_y2": "21.84",
            "_width": "0.05",
            "_layer": "39"
          },
          {
            "_x1": "-2.97",
            "_y1": "-21.59",
            "_x2": "-2.97",
            "_y2": "-23.495",
            "_width": "0.127",
            "_layer": "51"
          },
          {
            "_x1": "-2.97",
            "_y1": "-23.495",
            "_x2": "3",
            "_y2": "-23.495",
            "_width": "0.127",
            "_layer": "51"
          },
          {
            "_x1": "3",
            "_y1": "-23.495",
            "_x2": "3",
            "_y2": "-21.59",
            "_width": "0.127",
            "_layer": "51"
          },
          {
            "_x1": "-9.14",
            "_y1": "-21.84",
            "_x2": "-3.22",
            "_y2": "-21.84",
            "_width": "0.05",
            "_layer": "39"
          },
          {
            "_x1": "-3.22",
            "_y1": "-21.84",
            "_x2": "-3.22",
            "_y2": "-23.745",
            "_width": "0.05",
            "_layer": "39"
          },
          {
            "_x1": "-3.22",
            "_y1": "-23.745",
            "_x2": "3.25",
            "_y2": "-23.745",
            "_width": "0.05",
            "_layer": "39"
          },
          {
            "_x1": "3.25",
            "_y1": "-23.745",
            "_x2": "3.25",
            "_y2": "-21.84",
            "_width": "0.05",
            "_layer": "39"
          },
          {
            "_x1": "3.25",
            "_y1": "-21.84",
            "_x2": "9.14",
            "_y2": "-21.84",
            "_width": "0.05",
            "_layer": "39"
          }
        ],
        "circle": [
          {
            "_x": "-10.2",
            "_y": "17.8",
            "_radius": "0.1",
            "_width": "0.2",
            "_layer": "21"
          },
          {
            "_x": "-10.2",
            "_y": "17.8",
            "_radius": "0.1",
            "_width": "0.2",
            "_layer": "51"
          }
        ],
        "text": [
          {
            "_x": "-9.2",
            "_y": "21.9",
            "_size": "1.778",
            "_layer": "25",
            "__text": ">NAME"
          },
          {
            "_x": "-9.3",
            "_y": "-28.78",
            "_size": "1.778",
            "_layer": "27",
            "__text": ">VALUE"
          }
        ],
        "pad": [
          {
            "_name": "1",
            "_x": "-7.62",
            "_y": "17.78",
            "_drill": "0.9",
            "_diameter": "1.8",
            "_shape": "square",
            "_rot": "R270"
          },
          {
            "_name": "2",
            "_x": "-7.62",
            "_y": "15.24",
            "_drill": "0.9",
            "_diameter": "1.8",
            "_rot": "R270"
          },
          {
            "_name": "3",
            "_x": "-7.62",
            "_y": "12.7",
            "_drill": "0.9",
            "_diameter": "1.8",
            "_rot": "R270"
          },
          {
            "_name": "4",
            "_x": "-7.62",
            "_y": "10.16",
            "_drill": "0.9",
            "_diameter": "1.8",
            "_rot": "R270"
          },
          {
            "_name": "5",
            "_x": "-7.62",
            "_y": "7.62",
            "_drill": "0.9",
            "_diameter": "1.8",
            "_rot": "R270"
          },
          {
            "_name": "6",
            "_x": "-7.62",
            "_y": "5.08",
            "_drill": "0.9",
            "_diameter": "1.8",
            "_rot": "R270"
          },
          {
            "_name": "7",
            "_x": "-7.62",
            "_y": "2.54",
            "_drill": "0.9",
            "_diameter": "1.8",
            "_rot": "R270"
          },
          {
            "_name": "8",
            "_x": "-7.62",
            "_y": "0",
            "_drill": "0.9",
            "_diameter": "1.8",
            "_rot": "R270"
          },
          {
            "_name": "9",
            "_x": "-7.62",
            "_y": "-2.54",
            "_drill": "0.9",
            "_diameter": "1.8",
            "_rot": "R270"
          },
          {
            "_name": "10",
            "_x": "-7.62",
            "_y": "-5.08",
            "_drill": "0.9",
            "_diameter": "1.8",
            "_rot": "R270"
          },
          {
            "_name": "11",
            "_x": "-7.62",
            "_y": "-7.62",
            "_drill": "0.9",
            "_diameter": "1.8",
            "_rot": "R270"
          },
          {
            "_name": "12",
            "_x": "-7.62",
            "_y": "-10.16",
            "_drill": "0.9",
            "_diameter": "1.8",
            "_rot": "R270"
          },
          {
            "_name": "13",
            "_x": "-7.62",
            "_y": "-12.7",
            "_drill": "0.9",
            "_diameter": "1.8",
            "_rot": "R270"
          },
          {
            "_name": "14",
            "_x": "-7.62",
            "_y": "-15.24",
            "_drill": "0.9",
            "_diameter": "1.8",
            "_rot": "R270"
          },
          {
            "_name": "15",
            "_x": "-7.62",
            "_y": "-17.78",
            "_drill": "0.9",
            "_diameter": "1.8",
            "_rot": "R270"
          },
          {
            "_name": "16",
            "_x": "7.62",
            "_y": "-17.78",
            "_drill": "0.9",
            "_diameter": "1.8",
            "_rot": "R90"
          },
          {
            "_name": "17",
            "_x": "7.62",
            "_y": "-15.24",
            "_drill": "0.9",
            "_diameter": "1.8",
            "_rot": "R90"
          },
          {
            "_name": "18",
            "_x": "7.62",
            "_y": "-12.7",
            "_drill": "0.9",
            "_diameter": "1.8",
            "_rot": "R90"
          },
          {
            "_name": "19",
            "_x": "7.62",
            "_y": "-10.16",
            "_drill": "0.9",
            "_diameter": "1.8",
            "_rot": "R90"
          },
          {
            "_name": "20",
            "_x": "7.62",
            "_y": "-7.62",
            "_drill": "0.9",
            "_diameter": "1.8",
            "_rot": "R90"
          },
          {
            "_name": "21",
            "_x": "7.62",
            "_y": "-5.08",
            "_drill": "0.9",
            "_diameter": "1.8",
            "_rot": "R90"
          },
          {
            "_name": "22",
            "_x": "7.62",
            "_y": "-2.54",
            "_drill": "0.9",
            "_diameter": "1.8",
            "_rot": "R90"
          },
          {
            "_name": "23",
            "_x": "7.62",
            "_y": "0",
            "_drill": "0.9",
            "_diameter": "1.8",
            "_rot": "R90"
          },
          {
            "_name": "24",
            "_x": "7.62",
            "_y": "2.54",
            "_drill": "0.9",
            "_diameter": "1.8",
            "_rot": "R90"
          },
          {
            "_name": "25",
            "_x": "7.62",
            "_y": "5.08",
            "_drill": "0.9",
            "_diameter": "1.8",
            "_rot": "R90"
          },
          {
            "_name": "26",
            "_x": "7.62",
            "_y": "7.62",
            "_drill": "0.9",
            "_diameter": "1.8",
            "_rot": "R90"
          },
          {
            "_name": "27",
            "_x": "7.62",
            "_y": "10.16",
            "_drill": "0.9",
            "_diameter": "1.8",
            "_rot": "R90"
          },
          {
            "_name": "28",
            "_x": "7.62",
            "_y": "12.7",
            "_drill": "0.9",
            "_diameter": "1.8",
            "_rot": "R90"
          },
          {
            "_name": "29",
            "_x": "7.62",
            "_y": "15.24",
            "_drill": "0.9",
            "_diameter": "1.8",
            "_rot": "R90"
          },
          {
            "_name": "30",
            "_x": "7.62",
            "_y": "17.78",
            "_drill": "0.9",
            "_diameter": "1.8",
            "_rot": "R90"
          }
        ],
        "_name": "Arduino Nano"
      },
      {
        "wire": [
          {
            "_x1": "-13.95",
            "_y1": "27.15",
            "_x2": "13.95",
            "_y2": "27.15",
            "_width": "0.127",
            "_layer": "51"
          },
          {
            "_x1": "13.95",
            "_y1": "27.15",
            "_x2": "13.95",
            "_y2": "-27.25",
            "_width": "0.127",
            "_layer": "51"
          },
          {
            "_x1": "13.95",
            "_y1": "-27.25",
            "_x2": "-13.95",
            "_y2": "-27.25",
            "_width": "0.127",
            "_layer": "51"
          },
          {
            "_x1": "-13.95",
            "_y1": "-27.25",
            "_x2": "-13.95",
            "_y2": "27.15",
            "_width": "0.127",
            "_layer": "51"
          },
          {
            "_x1": "-13.95",
            "_y1": "-27.25",
            "_x2": "-13.95",
            "_y2": "27.15",
            "_width": "0.127",
            "_layer": "21"
          },
          {
            "_x1": "-13.95",
            "_y1": "27.15",
            "_x2": "13.95",
            "_y2": "27.15",
            "_width": "0.127",
            "_layer": "21"
          },
          {
            "_x1": "13.95",
            "_y1": "27.15",
            "_x2": "13.95",
            "_y2": "-27.25",
            "_width": "0.127",
            "_layer": "21"
          },
          {
            "_x1": "13.95",
            "_y1": "-27.25",
            "_x2": "-13.95",
            "_y2": "-27.25",
            "_width": "0.127",
            "_layer": "21"
          },
          {
            "_x1": "-14.2",
            "_y1": "27.4",
            "_x2": "14.2",
            "_y2": "27.4",
            "_width": "0.05",
            "_layer": "39"
          },
          {
            "_x1": "14.2",
            "_y1": "27.4",
            "_x2": "14.2",
            "_y2": "-27.5",
            "_width": "0.05",
            "_layer": "39"
          },
          {
            "_x1": "14.2",
            "_y1": "-27.5",
            "_x2": "-14.2",
            "_y2": "-27.5",
            "_width": "0.05",
            "_layer": "39"
          },
          {
            "_x1": "-14.2",
            "_y1": "-27.5",
            "_x2": "-14.2",
            "_y2": "27.4",
            "_width": "0.05",
            "_layer": "39"
          }
        ],
        "text": [
          {
            "_x": "-14.0054",
            "_y": "27.8108",
            "_size": "1.27049",
            "_layer": "25",
            "__text": ">NAME"
          },
          {
            "_x": "-14.0146",
            "_y": "-28.9302",
            "_size": "1.27133",
            "_layer": "27",
            "__text": ">VALUE"
          }
        ],
        "circle": [
          {
            "_x": "-14.6",
            "_y": "19.76",
            "_radius": "0.1",
            "_width": "0.2",
            "_layer": "21"
          },
          {
            "_x": "-14.6",
            "_y": "19.76",
            "_radius": "0.1",
            "_width": "0.2",
            "_layer": "51"
          }
        ],
        "pad": [
          {
            "_name": "J2-1",
            "_x": "-12.7",
            "_y": "19.76",
            "_drill": "1.04",
            "_shape": "square"
          },
          {
            "_name": "J2-2",
            "_x": "-12.7",
            "_y": "17.22",
            "_drill": "1.04"
          },
          {
            "_name": "J2-19",
            "_x": "-12.7",
            "_y": "-25.96",
            "_drill": "1.04"
          },
          {
            "_name": "J2-3",
            "_x": "-12.7",
            "_y": "14.68",
            "_drill": "1.04"
          },
          {
            "_name": "J2-4",
            "_x": "-12.7",
            "_y": "12.14",
            "_drill": "1.04"
          },
          {
            "_name": "J2-5",
            "_x": "-12.7",
            "_y": "9.6",
            "_drill": "1.04"
          },
          {
            "_name": "J2-6",
            "_x": "-12.7",
            "_y": "7.06",
            "_drill": "1.04"
          },
          {
            "_name": "J2-7",
            "_x": "-12.7",
            "_y": "4.52",
            "_drill": "1.04"
          },
          {
            "_name": "J2-8",
            "_x": "-12.7",
            "_y": "1.98",
            "_drill": "1.04"
          },
          {
            "_name": "J2-9",
            "_x": "-12.7",
            "_y": "-0.56",
            "_drill": "1.04"
          },
          {
            "_name": "J2-10",
            "_x": "-12.7",
            "_y": "-3.1",
            "_drill": "1.04"
          },
          {
            "_name": "J2-11",
            "_x": "-12.7",
            "_y": "-5.64",
            "_drill": "1.04"
          },
          {
            "_name": "J2-12",
            "_x": "-12.7",
            "_y": "-8.18",
            "_drill": "1.04"
          },
          {
            "_name": "J2-13",
            "_x": "-12.7",
            "_y": "-10.72",
            "_drill": "1.04"
          },
          {
            "_name": "J2-14",
            "_x": "-12.7",
            "_y": "-13.26",
            "_drill": "1.04"
          },
          {
            "_name": "J2-15",
            "_x": "-12.7",
            "_y": "-15.8",
            "_drill": "1.04"
          },
          {
            "_name": "J2-16",
            "_x": "-12.7",
            "_y": "-18.34",
            "_drill": "1.04"
          },
          {
            "_name": "J2-17",
            "_x": "-12.7",
            "_y": "-20.88",
            "_drill": "1.04"
          },
          {
            "_name": "J2-18",
            "_x": "-12.7",
            "_y": "-23.42",
            "_drill": "1.04"
          },
          {
            "_name": "J3-1",
            "_x": "12.7",
            "_y": "19.76",
            "_drill": "1.04"
          },
          {
            "_name": "J3-2",
            "_x": "12.7",
            "_y": "17.22",
            "_drill": "1.04"
          },
          {
            "_name": "J3-3",
            "_x": "12.7",
            "_y": "14.68",
            "_drill": "1.04"
          },
          {
            "_name": "J3-4",
            "_x": "12.7",
            "_y": "12.14",
            "_drill": "1.04"
          },
          {
            "_name": "J3-5",
            "_x": "12.7",
            "_y": "9.6",
            "_drill": "1.04"
          },
          {
            "_name": "J3-6",
            "_x": "12.7",
            "_y": "7.06",
            "_drill": "1.04"
          },
          {
            "_name": "J3-7",
            "_x": "12.7",
            "_y": "4.52",
            "_drill": "1.04"
          },
          {
            "_name": "J3-8",
            "_x": "12.7",
            "_y": "1.98",
            "_drill": "1.04"
          },
          {
            "_name": "J3-9",
            "_x": "12.7",
            "_y": "-0.56",
            "_drill": "1.04"
          },
          {
            "_name": "J3-10",
            "_x": "12.7",
            "_y": "-3.1",
            "_drill": "1.04"
          },
          {
            "_name": "J3-11",
            "_x": "12.7",
            "_y": "-5.64",
            "_drill": "1.04"
          },
          {
            "_name": "J3-12",
            "_x": "12.7",
            "_y": "-8.18",
            "_drill": "1.04"
          },
          {
            "_name": "J3-13",
            "_x": "12.7",
            "_y": "-10.72",
            "_drill": "1.04"
          },
          {
            "_name": "J3-14",
            "_x": "12.7",
            "_y": "-13.26",
            "_drill": "1.04"
          },
          {
            "_name": "J3-15",
            "_x": "12.7",
            "_y": "-15.8",
            "_drill": "1.04"
          },
          {
            "_name": "J3-16",
            "_x": "12.7",
            "_y": "-18.34",
            "_drill": "1.04"
          },
          {
            "_name": "J3-17",
            "_x": "12.7",
            "_y": "-20.88",
            "_drill": "1.04"
          },
          {
            "_name": "J3-18",
            "_x": "12.7",
            "_y": "-23.42",
            "_drill": "1.04"
          },
          {
            "_name": "J3-19",
            "_x": "12.7",
            "_y": "-25.96",
            "_drill": "1.04"
          }
        ],
        "_name": "ESP-32 DEV Kit"
      },
      {
        "text": [
          {
            "_x": "-13.0175",
            "_y": "26.035",
            "_size": "1.27",
            "_layer": "25",
            "__text": ">NAME"
          },
          {
            "_x": "-12.7",
            "_y": "-21.2725",
            "_size": "1.27",
            "_layer": "27",
            "__text": ">VALUE"
          }
        ],
        "wire": [
          {
            "_x1": "-12.7",
            "_y1": "19.45",
            "_x2": "-9",
            "_y2": "19.45",
            "_width": "0.127",
            "_layer": "51"
          },
          {
            "_x1": "9",
            "_y1": "19.45",
            "_x2": "12.7",
            "_y2": "19.45",
            "_width": "0.127",
            "_layer": "51"
          },
          {
            "_x1": "12.7",
            "_y1": "19.45",
            "_x2": "12.7",
            "_y2": "-19.45",
            "_width": "0.127",
            "_layer": "51"
          },
          {
            "_x1": "12.7",
            "_y1": "-19.45",
            "_x2": "4.1",
            "_y2": "-19.45",
            "_width": "0.127",
            "_layer": "51"
          },
          {
            "_x1": "-4.1",
            "_y1": "-19.45",
            "_x2": "-12.7",
            "_y2": "-19.45",
            "_width": "0.127",
            "_layer": "51"
          },
          {
            "_x1": "-12.7",
            "_y1": "-19.45",
            "_x2": "-12.7",
            "_y2": "19.45",
            "_width": "0.127",
            "_layer": "51"
          },
          {
            "_x1": "-9",
            "_y1": "19.45",
            "_x2": "-9",
            "_y2": "25.45",
            "_width": "0.127",
            "_layer": "51"
          },
          {
            "_x1": "-9",
            "_y1": "25.45",
            "_x2": "9",
            "_y2": "25.45",
            "_width": "0.127",
            "_layer": "51"
          },
          {
            "_x1": "9",
            "_y1": "25.45",
            "_x2": "9",
            "_y2": "19.45",
            "_width": "0.127",
            "_layer": "51"
          },
          {
            "_x1": "-4.1",
            "_y1": "-19.45",
            "_x2": "-4.1",
            "_y2": "-20.4",
            "_width": "0.127",
            "_layer": "51"
          },
          {
            "_x1": "-4.1",
            "_y1": "-20.4",
            "_x2": "4.1",
            "_y2": "-20.4",
            "_width": "0.127",
            "_layer": "51"
          },
          {
            "_x1": "4.1",
            "_y1": "-20.4",
            "_x2": "4.1",
            "_y2": "-19.45",
            "_width": "0.127",
            "_layer": "51"
          },
          {
            "_x1": "-12.7",
            "_y1": "19.45",
            "_x2": "-9",
            "_y2": "19.45",
            "_width": "0.127",
            "_layer": "21"
          },
          {
            "_x1": "9",
            "_y1": "19.45",
            "_x2": "12.7",
            "_y2": "19.45",
            "_width": "0.127",
            "_layer": "21"
          },
          {
            "_x1": "12.7",
            "_y1": "19.45",
            "_x2": "12.7",
            "_y2": "-19.45",
            "_width": "0.127",
            "_layer": "21"
          },
          {
            "_x1": "12.7",
            "_y1": "-19.45",
            "_x2": "4.1",
            "_y2": "-19.45",
            "_width": "0.127",
            "_layer": "21"
          },
          {
            "_x1": "-4.1",
            "_y1": "-19.45",
            "_x2": "-12.7",
            "_y2": "-19.45",
            "_width": "0.127",
            "_layer": "21"
          },
          {
            "_x1": "-12.7",
            "_y1": "-19.45",
            "_x2": "-12.7",
            "_y2": "19.45",
            "_width": "0.127",
            "_layer": "21"
          },
          {
            "_x1": "-9",
            "_y1": "19.45",
            "_x2": "-9",
            "_y2": "25.45",
            "_width": "0.127",
            "_layer": "21"
          },
          {
            "_x1": "-9",
            "_y1": "25.45",
            "_x2": "9",
            "_y2": "25.45",
            "_width": "0.127",
            "_layer": "21"
          },
          {
            "_x1": "9",
            "_y1": "25.45",
            "_x2": "9",
            "_y2": "19.45",
            "_width": "0.127",
            "_layer": "21"
          },
          {
            "_x1": "-4.1",
            "_y1": "-19.45",
            "_x2": "-4.1",
            "_y2": "-20.4",
            "_width": "0.127",
            "_layer": "21"
          },
          {
            "_x1": "-4.1",
            "_y1": "-20.4",
            "_x2": "4.1",
            "_y2": "-20.4",
            "_width": "0.127",
            "_layer": "21"
          },
          {
            "_x1": "4.1",
            "_y1": "-20.4",
            "_x2": "4.1",
            "_y2": "-19.45",
            "_width": "0.127",
            "_layer": "21"
          },
          {
            "_x1": "-12.95",
            "_y1": "19.7",
            "_x2": "-9.25",
            "_y2": "19.7",
            "_width": "0.05",
            "_layer": "39"
          },
          {
            "_x1": "9.25",
            "_y1": "19.7",
            "_x2": "12.95",
            "_y2": "19.7",
            "_width": "0.05",
            "_layer": "39"
          },
          {
            "_x1": "12.95",
            "_y1": "19.7",
            "_x2": "12.95",
            "_y2": "-19.7",
            "_width": "0.05",
            "_layer": "39"
          },
          {
            "_x1": "12.95",
            "_y1": "-19.7",
            "_x2": "4.35",
            "_y2": "-19.7",
            "_width": "0.05",
            "_layer": "39"
          },
          {
            "_x1": "-4.35",
            "_y1": "-19.7",
            "_x2": "-12.95",
            "_y2": "-19.7",
            "_width": "0.05",
            "_layer": "39"
          },
          {
            "_x1": "-12.95",
            "_y1": "-19.7",
            "_x2": "-12.95",
            "_y2": "19.7",
            "_width": "0.05",
            "_layer": "39"
          },
          {
            "_x1": "-9.25",
            "_y1": "19.7",
            "_x2": "-9.25",
            "_y2": "25.7",
            "_width": "0.05",
            "_layer": "39"
          },
          {
            "_x1": "-9.25",
            "_y1": "25.7",
            "_x2": "9.25",
            "_y2": "25.7",
            "_width": "0.05",
            "_layer": "39"
          },
          {
            "_x1": "9.25",
            "_y1": "25.7",
            "_x2": "9.25",
            "_y2": "19.7",
            "_width": "0.05",
            "_layer": "39"
          },
          {
            "_x1": "-4.35",
            "_y1": "-19.7",
            "_x2": "-4.35",
            "_y2": "-20.65",
            "_width": "0.05",
            "_layer": "39"
          },
          {
            "_x1": "-4.35",
            "_y1": "-20.65",
            "_x2": "4.35",
            "_y2": "-20.65",
            "_width": "0.05",
            "_layer": "39"
          },
          {
            "_x1": "4.35",
            "_y1": "-20.65",
            "_x2": "4.35",
            "_y2": "-19.7",
            "_width": "0.05",
            "_layer": "39"
          }
        ],
        "circle": [
          {
            "_x": "-13.25",
            "_y": "17.4",
            "_radius": "0.1",
            "_width": "0.2",
            "_layer": "21"
          },
          {
            "_x": "-13.25",
            "_y": "17.4",
            "_radius": "0.1",
            "_width": "0.2",
            "_layer": "51"
          }
        ],
        "pad": [
          {
            "_name": "J2_1",
            "_x": "-11.43",
            "_y": "17.4",
            "_drill": "1.016",
            "_shape": "square"
          },
          {
            "_name": "J3_1",
            "_x": "11.43",
            "_y": "17.4",
            "_drill": "1.016"
          },
          {
            "_name": "J2_2",
            "_x": "-11.43",
            "_y": "14.86",
            "_drill": "1.016"
          },
          {
            "_name": "J3_2",
            "_x": "11.43",
            "_y": "14.86",
            "_drill": "1.016"
          },
          {
            "_name": "J2_3",
            "_x": "-11.43",
            "_y": "12.32",
            "_drill": "1.016"
          },
          {
            "_name": "J3_3",
            "_x": "11.43",
            "_y": "12.32",
            "_drill": "1.016"
          },
          {
            "_name": "J2_4",
            "_x": "-11.43",
            "_y": "9.78",
            "_drill": "1.016"
          },
          {
            "_name": "J3_4",
            "_x": "11.43",
            "_y": "9.78",
            "_drill": "1.016"
          },
          {
            "_name": "J2_5",
            "_x": "-11.43",
            "_y": "7.24",
            "_drill": "1.016"
          },
          {
            "_name": "J3_5",
            "_x": "11.43",
            "_y": "7.24",
            "_drill": "1.016"
          },
          {
            "_name": "J2_6",
            "_x": "-11.43",
            "_y": "4.7",
            "_drill": "1.016"
          },
          {
            "_name": "J3_6",
            "_x": "11.43",
            "_y": "4.7",
            "_drill": "1.016"
          },
          {
            "_name": "J2_7",
            "_x": "-11.43",
            "_y": "2.16",
            "_drill": "1.016"
          },
          {
            "_name": "J3_7",
            "_x": "11.43",
            "_y": "2.16",
            "_drill": "1.016"
          },
          {
            "_name": "J2_8",
            "_x": "-11.43",
            "_y": "-0.38",
            "_drill": "1.016"
          },
          {
            "_name": "J3_8",
            "_x": "11.43",
            "_y": "-0.38",
            "_drill": "1.016"
          },
          {
            "_name": "J2_9",
            "_x": "-11.43",
            "_y": "-2.92",
            "_drill": "1.016"
          },
          {
            "_name": "J3_9",
            "_x": "11.43",
            "_y": "-2.92",
            "_drill": "1.016"
          },
          {
            "_name": "J2_10",
            "_x": "-11.43",
            "_y": "-5.46",
            "_drill": "1.016"
          },
          {
            "_name": "J3_10",
            "_x": "11.43",
            "_y": "-5.46",
            "_drill": "1.016"
          },
          {
            "_name": "J2_11",
            "_x": "-11.43",
            "_y": "-8",
            "_drill": "1.016"
          },
          {
            "_name": "J3_11",
            "_x": "11.43",
            "_y": "-8",
            "_drill": "1.016"
          },
          {
            "_name": "J2_12",
            "_x": "-11.43",
            "_y": "-10.54",
            "_drill": "1.016"
          },
          {
            "_name": "J3_12",
            "_x": "11.43",
            "_y": "-10.54",
            "_drill": "1.016"
          },
          {
            "_name": "J2_13",
            "_x": "-11.43",
            "_y": "-13.08",
            "_drill": "1.016"
          },
          {
            "_name": "J3_13",
            "_x": "11.43",
            "_y": "-13.08",
            "_drill": "1.016"
          },
          {
            "_name": "J2_14",
            "_x": "-11.43",
            "_y": "-15.62",
            "_drill": "1.016"
          },
          {
            "_name": "J3_14",
            "_x": "11.43",
            "_y": "-15.62",
            "_drill": "1.016"
          },
          {
            "_name": "J2_15",
            "_x": "-11.43",
            "_y": "-18.16",
            "_drill": "1.016"
          },
          {
            "_name": "J3_15",
            "_x": "11.43",
            "_y": "-18.16",
            "_drill": "1.016"
          }
        ],
        "_name": "ESP-8266 DEV Kit"
      }
    ]
  }